service_streamer/__init__.py
service_streamer/managed_model.py
service_streamer/service_streamer.py
ym_service_streamer-1.0.5.dist-info/LICENSE
ym_service_streamer-1.0.5.dist-info/METADATA
ym_service_streamer-1.0.5.dist-info/WHEEL
ym_service_streamer-1.0.5.dist-info/top_level.txt
ym_service_streamer-1.0.5.dist-info/RECORD
