Metadata-Version: 2.1
Name: ym-service-streamer
Version: 1.0.5
Summary: Boosting your web service of deep learning applications
Home-page: https://github.com/yimian/service-streamer
License: UNKNOWN
Keywords: service_streamer
Platform: UNKNOWN
Classifier: Development Status :: 3 - Alpha
Classifier: Programming Language :: Python :: 3.5
Classifier: Programming Language :: Python :: 3.6
Classifier: Programming Language :: Python :: 3.7
Classifier: Programming Language :: Python :: Implementation :: CPython
Classifier: Operating System :: OS Independent
Requires-Python: >=3.5
Requires-Dist: redis
Requires-Dist: tqdm
